Metadata-Version: 2.3
Name: anthropic
Version: 0.68.2
Summary: The official Python library for the anthropic API
Project-URL: Homepage, https://github.com/anthropics/anthropic-sdk-python
Project-URL: Repository, https://github.com/anthropics/anthropic-sdk-python
Author-email: Anthropic <support@anthropic.com>
License: MIT
Classifier: Intended Audience :: Developers
Classifier: License :: OSI Approved :: MIT License
Classifier: Operating System :: MacOS
Classifier: Operating System :: Microsoft :: Windows
Classifier: Operating System :: OS Independent
Classifier: Operating System :: POSIX
Classifier: Operating System :: POSIX :: Linux
Classifier: Programming Language :: Python :: 3.8
Classifier: Programming Language :: Python :: 3.9
Classifier: Programming Language :: Python :: 3.10
Classifier: Programming Language :: Python :: 3.11
Classifier: Programming Language :: Python :: 3.12
Classifier: Programming Language :: Python :: 3.13
Classifier: Topic :: Software Development :: Libraries :: Python Modules
Classifier: Typing :: Typed
Requires-Python: >=3.8
Requires-Dist: anyio<5,>=3.5.0
Requires-Dist: distro<2,>=1.7.0
Requires-Dist: docstring-parser<1,>=0.15
Requires-Dist: httpx<1,>=0.25.0
Requires-Dist: jiter<1,>=0.4.0
Requires-Dist: pydantic<3,>=1.9.0
Requires-Dist: sniffio
Requires-Dist: typing-extensions<5,>=4.10
Provides-Extra: aiohttp
Requires-Dist: aiohttp; extra == 'aiohttp'
Requires-Dist: httpx-aiohttp>=0.1.8; extra == 'aiohttp'
Provides-Extra: bedrock
Requires-Dist: boto3>=1.28.57; extra == 'bedrock'
Requires-Dist: botocore>=1.31.57; extra == 'bedrock'
Provides-Extra: vertex
Requires-Dist: google-auth[requests]<3,>=2; extra == 'vertex'
